{"IJWCW6FUp9bBu2LlwbPKMg==":"nba-240x533.png","PG+yo8PACFwdJVfgLAsq9g==":"%E7%88%B1%E5%A5%87%E8%89%BA-240x111.png","+Fkp/lIRmwWL7hydsgRK9A==":"%E6%88%B4%E5%B0%94-240x240.png","bFdxh+GACUHMn3WkF/sGaQ==":"%E4%B8%9C%E4%BA%AC%E5%A1%94-240x240.png","bR6/ScO6xGBWmnvpmuKC2Q==":"%E6%9D%B1%E6%98%A0-240x53.png","xdT0oVv+AVoTacpthk6Iuw==":"%E8%BF%91%E9%93%81%E7%99%BE%E8%B4%A7-240x180.png","Tcsy8K7igDEE+dGpQksR1Q==":"%E4%B9%90%E5%A4%A9-240x71.png","aXv/9zXzW5TyHJTXXo8+0g==":"%E7%BD%91%E6%98%93%E8%8B%B1%E6%96%87-118x45.png","KT+YGEEPHurL+GX2otqPzg==":"%E7%BD%91%E6%98%93%E4%B8%AD%E6%96%87-177x58.png","OubDvfg7pNd2CH9TllSdYw==":"%E5%B0%8F%E5%B2%9B%E7%A7%80%E5%A4%AB-236x256.png","mipxaD6QcE0YLtPMSm4SPw==":"%E5%AE%9C%E5%AE%B6-236x94.png","fy5Seumq1vH0M7SMoMcLQA==":"%E6%B8%B8%E6%97%8F%E7%BD%91%E7%BB%9C-124x40.png","jarD2jswlZCKj5TYrSn/qw==":"mbr-1080x720.jpg","ife/RuIzCgI1ZGlqLMh1EA==":"background1.jpg","pb6EBv1N9hFJVDxyhUnh3Q==":"mbr-1-1080x720.jpg","+c3M3HUHlxUwPXJ62jkwqw==":"%E6%88%AA%E5%B1%8F2021-01-17%2013.57.57-699x393.png","zpFQY/AcpnfS123a1Cew6A==":"%E6%88%AA%E5%B1%8F2021-01-17%2014.22.51-699x393.png","t01gF5imkU1ZHFcT+zLRrA==":"%E6%88%AA%E5%B1%8F2021-01-17%2016.52.15-699x393.png","KEnZuB2QJJXZ4mfCovpw6w==":"%E6%88%AA%E5%B1%8F2021-01-17%2016.43.04-699x393.png","QFKDys8Yvos4wqjH3cbZqA==":"%E6%88%AA%E5%B1%8F2021-01-17%2014.06.25-699x393.png","BJNS9pGHBcBREf1ZPopbBA==":"%E5%BE%AE%E4%BF%A1%E6%88%AA%E5%9B%BE-20210314121518-121x33.png","2IIqNgQYg5UrEbMzEjnofA==":"%E5%BE%AE%E4%BF%A1%E6%88%AA%E5%9B%BE-20210314121518-121x33.png","d4jzNlQfrq/ZAeA3k6xzaw==":"%E6%88%AA%E5%B1%8F2021-01-17%2016.49.50-2000x1125.png","+KFhgmFqVJ6+1md3yKNUYQ==":"%E6%88%AA%E5%B1%8F2021-01-17%2016.49.50-85x48.png","HMhF4VvJOx2QzVOglRPuoA==":"%E6%88%AA%E5%B1%8F2021-01-17%2016.49.50-1024x576.png","0HSaqeiYlufG9/yLupbuqg==":"%E6%88%AA%E5%B1%8F2021-01-17%2013.59.54-2000x1125.png","hoKKANcAyYLT0SmknDLfIQ==":"%E6%88%AA%E5%B1%8F2021-01-17%2013.59.54-85x48.png","kiDTgUkkCgtBQnLxl11wPg==":"%E6%88%AA%E5%B1%8F2021-01-17%2013.59.54-1024x576.png","FebTjjCd1zA04VC0PENqlg==":"%E6%88%AA%E5%B1%8F2021-01-17%2014.10.46-2000x1125.png","Ss/LkIHGD1+rcyhkUlnS9g==":"%E6%88%AA%E5%B1%8F2021-01-17%2014.10.46-85x48.png","8mhvSjegSkJzsSYCGjkfIA==":"%E6%88%AA%E5%B1%8F2021-01-17%2014.10.46-1024x576.png","2s5bHL0ZvFkXgeK27PVGYA==":"%E6%88%AA%E5%B1%8F2021-01-17%2016.48.12-2000x1125.png"}